.clang-format
.flake8
.gitignore
.gitmodules
CHANGELOG.md
CODEOWNERS
CODE_OF_CONDUCT
Dockerfile
Dockerfile-cuda
Dockerfile-embedded
LICENSE
MANIFEST.in
Makefile
README.md
__init__.py
description.txt
packages.txt
setup.py
./src/opendr/__init__.py
./src/opendr/_setup.py
./src/opendr/_version.py
./src/opendr/control/__init__.py
./src/opendr/engine/__init__.py
./src/opendr/engine/constants.py
./src/opendr/engine/data.py
./src/opendr/engine/datasets.py
./src/opendr/engine/example_learner.py
./src/opendr/engine/learners.py
./src/opendr/engine/target.py
./src/opendr/perception/__init__.py
./src/opendr/perception/activity_recognition/README.md
./src/opendr/perception/activity_recognition/__init__.py
./src/opendr/perception/activity_recognition/dependencies.ini
./src/opendr/perception/activity_recognition/continual_transformer_encoder/__init__.py
./src/opendr/perception/activity_recognition/continual_transformer_encoder/continual_transformer_encoder_learner.py
./src/opendr/perception/activity_recognition/cox3d/__init__.py
./src/opendr/perception/activity_recognition/cox3d/cox3d_learner.py
./src/opendr/perception/activity_recognition/cox3d/algorithm/__init__.py
./src/opendr/perception/activity_recognition/cox3d/algorithm/res.py
./src/opendr/perception/activity_recognition/cox3d/algorithm/se.py
./src/opendr/perception/activity_recognition/cox3d/algorithm/x3d.py
./src/opendr/perception/activity_recognition/datasets/__init__.py
./src/opendr/perception/activity_recognition/datasets/dummy_timeseries_dataset.py
./src/opendr/perception/activity_recognition/datasets/kinetics.py
./src/opendr/perception/activity_recognition/datasets/kinetics400_classes.csv
./src/opendr/perception/activity_recognition/datasets/utils/__init__.py
./src/opendr/perception/activity_recognition/datasets/utils/decoder.py
./src/opendr/perception/activity_recognition/datasets/utils/transforms.py
./src/opendr/perception/activity_recognition/utils/__init__.py
./src/opendr_toolkit_activity_recognition.egg-info/PKG-INFO
./src/opendr_toolkit_activity_recognition.egg-info/SOURCES.txt
./src/opendr_toolkit_activity_recognition.egg-info/dependency_links.txt
./src/opendr_toolkit_activity_recognition.egg-info/requires.txt
./src/opendr_toolkit_activity_recognition.egg-info/top_level.txt
